{
    "version": "0.2.2",
    "description": "Multi-engine, subtitle downloader",
    "homepage": "https://qnapi.github.io/",
    "license": "GPL-2.0-or-later",
    "url": "https://github.com/QNapi/qnapi/releases/download/0.2.2/QNapi-0.2.2-portable.zip",
    "hash": "5380b2fc1f99f91bb3d6afcefef0444d17e07a979d1e4c0b6194dc62a47653c7",
    "extract_dir": "QNapi",
    "bin": "qnapi.exe",
    "shortcuts": [
        [
            "qnapi.exe",
            "QNapi"
        ]
    ],
    "persist": "qnapi.ini",
    "checkver": {
        "github": "https://github.com/QNapi/qnapi"
    },
    "autoupdate": {
        "url": "https://github.com/QNapi/qnapi/releases/download/$version/QNapi-$version-portable.zip"
    }
}
